rubaialter/__init__.py
rubaialter/__main__.py
rubaialter/converter.py
rubaialter/csv_to.py
rubaialter/sqlite_to.py
rubaialter/xls_xlsx_to.py
rubaialter-1.1.0b1.dist-info/LICENSE.txt
rubaialter-1.1.0b1.dist-info/METADATA
rubaialter-1.1.0b1.dist-info/WHEEL
rubaialter-1.1.0b1.dist-info/entry_points.txt
rubaialter-1.1.0b1.dist-info/top_level.txt
rubaialter-1.1.0b1.dist-info/RECORD
