Metadata-Version: 2.1
Name: rubaialter
Version: 1.1.0b1
Summary: A module for altering numerical dataset's formats, made on top of Pandas.
Home-page: https://github.com/TechLearnersInc/rubaialter
Author: Muhammad Sakib Khan Inan
Author-email: sakib.khaninan@gmail.com
License: MIT
Project-URL: Source, https://github.com/TechLearnersInc/rubaialter
Project-URL: Tracker, https://github.com/TechLearnersInc/rubaialter/issues
Project-URL: Facebook, https://www.facebook.com/TechLearnersInc
Project-URL: Linkedin, https://www.linkedin.com/company/techlearners/
Project-URL: Telegram, https://t.me/TechLearners
Keywords: pandas rubaialter csv xls excel xlsx sqlite sqlite3 converter dataset
Platform: UNKNOWN
Classifier: Development Status :: 4 - Beta
Classifier: Environment :: Console
Classifier: Intended Audience :: Developers
Classifier: Intended Audience :: Science/Research
Classifier: Topic :: Utilities
Classifier: License :: OSI Approved :: MIT License
Classifier: Programming Language :: Python :: 3
Classifier: Programming Language :: Python :: 3.6
Classifier: Programming Language :: Python :: 3.7
Classifier: Programming Language :: Python :: 3.8
Classifier: Programming Language :: Python :: 3.9
Requires-Python: >=3.6
Requires-Dist: openpyxl
Requires-Dist: pandas
Requires-Dist: xlrd
Requires-Dist: xlwt
